co2cli_pkg/__init__.py
co2cli_pkg/__main__.py
co2cli_pkg/funcmodule.py
co2cli_pkg-0.0.1.dist-info/LICENSE
co2cli_pkg-0.0.1.dist-info/METADATA
co2cli_pkg-0.0.1.dist-info/WHEEL
co2cli_pkg-0.0.1.dist-info/entry_points.txt
co2cli_pkg-0.0.1.dist-info/top_level.txt
co2cli_pkg-0.0.1.dist-info/RECORD
