Metadata-Version: 2.1
Name: co2cli-pkg
Version: 0.0.1
Summary: A package to calculate the CO2 emissions
Home-page: https://github.com/PiyushD17/CO2-CLI
Author: Piyush Dongre
Author-email: piyush.dongre@yahoo.com
License: UNKNOWN
Platform: UNKNOWN
Classifier: Programming Language :: Python :: 3
Classifier: License :: OSI Approved :: MIT License
Classifier: Operating System :: OS Independent
Requires-Python: >=3.5
Requires-Dist: click (==7.1.2)
